ggea/__init__.py
ggea/ggea.py
ggea-0.0.5.dist-info/METADATA
ggea-0.0.5.dist-info/RECORD
ggea-0.0.5.dist-info/WHEEL
ggea-0.0.5.dist-info/top_level.txt
