Metadata-Version: 2.1
Name: ggea
Version: 0.0.5
Summary: Asynchronous State Graph Generator
Home-page: https://github.com/clement-alexandre/TotemBionet
Author: Alexandre Clement
Author-email: alexandre.clement@etu.unice.fr
License: WTFPL
Keywords: jupyter,computational systems biology
Platform: UNKNOWN
Classifier: Intended Audience :: Science/Research
Classifier: Topic :: Scientific/Engineering :: Bio-Informatics
Classifier: Programming Language :: Python :: 3.6
Classifier: Programming Language :: Python :: 3.7
Provides-Extra: ipython
Requires-Dist: discrete-model
Requires-Dist: matplotlib (>=3.0.0)
Requires-Dist: pydot
Requires-Dist: networkx (>=2.0)
Provides-Extra: ipython
Requires-Dist: tabulate; extra == 'ipython'
